event_scraper_generics/__init__.py
event_scraper_generics/abc_publisher.py
event_scraper_generics/abc_scraper.py
event_scraper_generics/types/__init__.py
event_scraper_generics/types/generics.py
event_scraper_generics/types/submission.py
event_scraper_generics-0.1.2.dist-info/METADATA
event_scraper_generics-0.1.2.dist-info/WHEEL
event_scraper_generics-0.1.2.dist-info/RECORD
